setup.py
govdhar_probability/BinomialDistribution.py
govdhar_probability/GaussianDistribution.py
govdhar_probability/GeneralDistributions.py
govdhar_probability/__init__.py
govdhar_probability/example_code.py
govdhar_probability.egg-info/PKG-INFO
govdhar_probability.egg-info/SOURCES.txt
govdhar_probability.egg-info/dependency_links.txt
govdhar_probability.egg-info/not-zip-safe
govdhar_probability.egg-info/top_level.txt