Metadata-Version: 2.1
Name: govdhar-probability
Version: 1.1
Summary: Gaussian and Binomial probabilities
Home-page: UNKNOWN
Author: Govind Dharwada
Author-email: govind.vyas@gmail.com
License: UNKNOWN
Platform: UNKNOWN
